http_sf/__init__.py
http_sf/__main__.py
http_sf/bare_item.py
http_sf/boolean.py
http_sf/byteseq.py
http_sf/date.py
http_sf/decimal.py
http_sf/dictionary.py
http_sf/display_string.py
http_sf/errors.py
http_sf/innerlist.py
http_sf/integer.py
http_sf/item.py
http_sf/list.py
http_sf/parameters.py
http_sf/py.typed
http_sf/retrofit.py
http_sf/state.py
http_sf/string.py
http_sf/token.py
http_sf/types.py
http_sf/util.py
http_sf-1.1.0.dist-info/licenses/LICENCE.md
test/harfile.py
test/test.py
test/test_callback.py
test/test_perf.py
test/test_position.py
http_sf-1.1.0.dist-info/METADATA
http_sf-1.1.0.dist-info/WHEEL
http_sf-1.1.0.dist-info/top_level.txt
http_sf-1.1.0.dist-info/RECORD
