Metadata-Version: 2.4
Name: http-sf
Version: 1.1.0
Summary: Parse and serialise HTTP Structured Fields
Author-email: Mark Nottingham <mnot@mnot.net>
Project-URL: homepage, https://github.com/mnot/http-sf
Classifier: Operating System :: OS Independent
Classifier: Development Status :: 4 - Beta
Classifier: License :: OSI Approved :: MIT License
Requires-Python: >=3.10
License-File: LICENCE.md
Requires-Dist: typing_extensions
Provides-Extra: dev
Requires-Dist: mypy; extra == "dev"
Requires-Dist: black; extra == "dev"
Requires-Dist: pylint; extra == "dev"
Requires-Dist: pytest; extra == "dev"
Requires-Dist: pytest-md; extra == "dev"
Requires-Dist: validate-pyproject; extra == "dev"
Requires-Dist: build; extra == "dev"
Dynamic: license-file
